[
  {
    "rank": 1,
    "nameAndTeamName": "清水 昇(ヤ)",
    "avg": 0,
    "hr": 0,
    "rbi": 0,
    "sb": 0,
    "obp": 0,
    "slg": 0,
    "ops": 0,
    "risp": 0,
    "era": 2.2,
    "win": 0,
    "lose": 3,
    "k": 30,
    "k9": 9.42,
    "hold": 20,
    "save": 1
  },
  {
    "rank": 2,
    "nameAndTeamName": "岩崎 優(神)",
    "avg": 0,
    "hr": 0,
    "rbi": 0,
    "sb": 0,
    "obp": 0,
    "slg": 0,
    "ops": 0,
    "risp": 0,
    "era": 3.09,
    "win": 1,
    "lose": 3,
    "k": 22,
    "k9": 8.49,
    "hold": 18,
    "save": 0
  },
  {
    "rank": 3,
    "nameAndTeamName": "又吉 克樹(中)",
    "avg": 0,
    "hr": 0,
    "rbi": 0,
    "sb": 0,
    "obp": 0,
    "slg": 0,
    "ops": 0,
    "risp": 0,
    "era": 1.19,
    "win": 0,
    "lose": 1,
    "k": 21,
    "k9": 6.23,
    "hold": 15,
    "save": 7
  },
  {
    "rank": 4,
    "nameAndTeamName": "山﨑 康晃(デ)",
    "avg": 0,
    "hr": 0,
    "rbi": 0,
    "sb": 0,
    "obp": 0,
    "slg": 0,
    "ops": 0,
    "risp": 0,
    "era": 2.08,
    "win": 3,
    "lose": 1,
    "k": 22,
    "k9": 6.53,
    "hold": 14,
    "save": 0
  },
  {
    "rank": 4,
    "nameAndTeamName": "マクガフ(ヤ)",
    "avg": 0,
    "hr": 0,
    "rbi": 0,
    "sb": 0,
    "obp": 0,
    "slg": 0,
    "ops": 0,
    "risp": 0,
    "era": 2.2,
    "win": 2,
    "lose": 1,
    "k": 39,
    "k9": 12.24,
    "hold": 14,
    "save": 10
  },
  {
    "rank": 4,
    "nameAndTeamName": "中川 皓太(巨)",
    "avg": 0,
    "hr": 0,
    "rbi": 0,
    "sb": 0,
    "obp": 0,
    "slg": 0,
    "ops": 0,
    "risp": 0,
    "era": 3.77,
    "win": 2,
    "lose": 2,
    "k": 33,
    "k9": 10.36,
    "hold": 14,
    "save": 1
  },
  {
    "rank": 7,
    "nameAndTeamName": "高梨 雄平(巨)",
    "avg": 0,
    "hr": 0,
    "rbi": 0,
    "sb": 0,
    "obp": 0,
    "slg": 0,
    "ops": 0,
    "risp": 0,
    "era": 0.6,
    "win": 1,
    "lose": 0,
    "k": 15,
    "k9": 9,
    "hold": 13,
    "save": 1
  },
  {
    "rank": 7,
    "nameAndTeamName": "塹江 敦哉(広)",
    "avg": 0,
    "hr": 0,
    "rbi": 0,
    "sb": 0,
    "obp": 0,
    "slg": 0,
    "ops": 0,
    "risp": 0,
    "era": 3.27,
    "win": 1,
    "lose": 2,
    "k": 15,
    "k9": 6.14,
    "hold": 13,
    "save": 0
  },
  {
    "rank": 9,
    "nameAndTeamName": "谷元 圭介(中)",
    "avg": 0,
    "hr": 0,
    "rbi": 0,
    "sb": 0,
    "obp": 0,
    "slg": 0,
    "ops": 0,
    "risp": 0,
    "era": 2.12,
    "win": 0,
    "lose": 1,
    "k": 12,
    "k9": 6.35,
    "hold": 12,
    "save": 0
  },
  {
    "rank": 9,
    "nameAndTeamName": "福 敬登(中)",
    "avg": 0,
    "hr": 0,
    "rbi": 0,
    "sb": 0,
    "obp": 0,
    "slg": 0,
    "ops": 0,
    "risp": 0,
    "era": 3.27,
    "win": 2,
    "lose": 1,
    "k": 17,
    "k9": 6.95,
    "hold": 12,
    "save": 0
  },
  {
    "rank": 9,
    "nameAndTeamName": "エスコバー(デ)",
    "avg": 0,
    "hr": 0,
    "rbi": 0,
    "sb": 0,
    "obp": 0,
    "slg": 0,
    "ops": 0,
    "risp": 0,
    "era": 3.33,
    "win": 2,
    "lose": 0,
    "k": 23,
    "k9": 8.51,
    "hold": 12,
    "save": 0
  },
  {
    "rank": 9,
    "nameAndTeamName": "岩貞 祐太(神)",
    "avg": 0,
    "hr": 0,
    "rbi": 0,
    "sb": 0,
    "obp": 0,
    "slg": 0,
    "ops": 0,
    "risp": 0,
    "era": 5.21,
    "win": 2,
    "lose": 0,
    "k": 20,
    "k9": 9.47,
    "hold": 12,
    "save": 0
  },
  {
    "rank": 13,
    "nameAndTeamName": "近藤 弘樹(ヤ)",
    "avg": 0,
    "hr": 0,
    "rbi": 0,
    "sb": 0,
    "obp": 0,
    "slg": 0,
    "ops": 0,
    "risp": 0,
    "era": 0.96,
    "win": 0,
    "lose": 1,
    "k": 17,
    "k9": 8.2,
    "hold": 11,
    "save": 0
  },
  {
    "rank": 14,
    "nameAndTeamName": "砂田 毅樹(デ)",
    "avg": 0,
    "hr": 0,
    "rbi": 0,
    "sb": 0,
    "obp": 0,
    "slg": 0,
    "ops": 0,
    "risp": 0,
    "era": 2.55,
    "win": 0,
    "lose": 1,
    "k": 18,
    "k9": 6.57,
    "hold": 9,
    "save": 0
  },
  {
    "rank": 14,
    "nameAndTeamName": "鍵谷 陽平(巨)",
    "avg": 0,
    "hr": 0,
    "rbi": 0,
    "sb": 0,
    "obp": 0,
    "slg": 0,
    "ops": 0,
    "risp": 0,
    "era": 2.89,
    "win": 2,
    "lose": 0,
    "k": 13,
    "k9": 6.27,
    "hold": 9,
    "save": 1
  },
  {
    "rank": 16,
    "nameAndTeamName": "大江 竜聖(巨)",
    "avg": 0,
    "hr": 0,
    "rbi": 0,
    "sb": 0,
    "obp": 0,
    "slg": 0,
    "ops": 0,
    "risp": 0,
    "era": 2.55,
    "win": 0,
    "lose": 0,
    "k": 13,
    "k9": 6.62,
    "hold": 8,
    "save": 0
  },
  {
    "rank": 17,
    "nameAndTeamName": "今野 龍太(ヤ)",
    "avg": 0,
    "hr": 0,
    "rbi": 0,
    "sb": 0,
    "obp": 0,
    "slg": 0,
    "ops": 0,
    "risp": 0,
    "era": 2.67,
    "win": 3,
    "lose": 0,
    "k": 27,
    "k9": 9,
    "hold": 7,
    "save": 0
  },
  {
    "rank": 17,
    "nameAndTeamName": "祖父江 大輔(中)",
    "avg": 0,
    "hr": 0,
    "rbi": 0,
    "sb": 0,
    "obp": 0,
    "slg": 0,
    "ops": 0,
    "risp": 0,
    "era": 3.91,
    "win": 1,
    "lose": 2,
    "k": 15,
    "k9": 5.87,
    "hold": 7,
    "save": 5
  },
  {
    "rank": 19,
    "nameAndTeamName": "馬場 皐輔(神)",
    "avg": 0,
    "hr": 0,
    "rbi": 0,
    "sb": 0,
    "obp": 0,
    "slg": 0,
    "ops": 0,
    "risp": 0,
    "era": 2.5,
    "win": 2,
    "lose": 0,
    "k": 15,
    "k9": 7.5,
    "hold": 6,
    "save": 0
  },
  {
    "rank": 19,
    "nameAndTeamName": "森浦 大輔(広)",
    "avg": 0,
    "hr": 0,
    "rbi": 0,
    "sb": 0,
    "obp": 0,
    "slg": 0,
    "ops": 0,
    "risp": 0,
    "era": 3.77,
    "win": 2,
    "lose": 2,
    "k": 7,
    "k9": 4.4,
    "hold": 6,
    "save": 0
  },
  {
    "rank": 19,
    "nameAndTeamName": "中田 廉(広)",
    "avg": 0,
    "hr": 0,
    "rbi": 0,
    "sb": 0,
    "obp": 0,
    "slg": 0,
    "ops": 0,
    "risp": 0,
    "era": 4,
    "win": 0,
    "lose": 0,
    "k": 14,
    "k9": 7,
    "hold": 6,
    "save": 0
  },
  {
    "rank": 22,
    "nameAndTeamName": "梅野 雄吾(ヤ)",
    "avg": 0,
    "hr": 0,
    "rbi": 0,
    "sb": 0,
    "obp": 0,
    "slg": 0,
    "ops": 0,
    "risp": 0,
    "era": 2.86,
    "win": 0,
    "lose": 0,
    "k": 27,
    "k9": 11.05,
    "hold": 5,
    "save": 0
  },
  {
    "rank": 23,
    "nameAndTeamName": "野上 亮磨(巨)",
    "avg": 0,
    "hr": 0,
    "rbi": 0,
    "sb": 0,
    "obp": 0,
    "slg": 0,
    "ops": 0,
    "risp": 0,
    "era": 1.65,
    "win": 0,
    "lose": 1,
    "k": 15,
    "k9": 8.27,
    "hold": 4,
    "save": 1
  },
  {
    "rank": 23,
    "nameAndTeamName": "小林 慶祐(神)",
    "avg": 0,
    "hr": 0,
    "rbi": 0,
    "sb": 0,
    "obp": 0,
    "slg": 0,
    "ops": 0,
    "risp": 0,
    "era": 2.81,
    "win": 0,
    "lose": 1,
    "k": 15,
    "k9": 8.44,
    "hold": 4,
    "save": 0
  },
  {
    "rank": 23,
    "nameAndTeamName": "坂本 光士郎(ヤ)",
    "avg": 0,
    "hr": 0,
    "rbi": 0,
    "sb": 0,
    "obp": 0,
    "slg": 0,
    "ops": 0,
    "risp": 0,
    "era": 3.54,
    "win": 1,
    "lose": 1,
    "k": 17,
    "k9": 7.52,
    "hold": 4,
    "save": 0
  },
  {
    "rank": 23,
    "nameAndTeamName": "桜井 俊貴(巨)",
    "avg": 0,
    "hr": 0,
    "rbi": 0,
    "sb": 0,
    "obp": 0,
    "slg": 0,
    "ops": 0,
    "risp": 0,
    "era": 4.4,
    "win": 0,
    "lose": 0,
    "k": 9,
    "k9": 5.65,
    "hold": 4,
    "save": 0
  },
  {
    "rank": 27,
    "nameAndTeamName": "藤嶋 健人(中)",
    "avg": 0,
    "hr": 0,
    "rbi": 0,
    "sb": 0,
    "obp": 0,
    "slg": 0,
    "ops": 0,
    "risp": 0,
    "era": 2.05,
    "win": 1,
    "lose": 0,
    "k": 18,
    "k9": 7.36,
    "hold": 3,
    "save": 0
  },
  {
    "rank": 27,
    "nameAndTeamName": "藤浪 晋太郎(神)",
    "avg": 0,
    "hr": 0,
    "rbi": 0,
    "sb": 0,
    "obp": 0,
    "slg": 0,
    "ops": 0,
    "risp": 0,
    "era": 2.27,
    "win": 2,
    "lose": 1,
    "k": 29,
    "k9": 8.24,
    "hold": 3,
    "save": 0
  },
  {
    "rank": 27,
    "nameAndTeamName": "大道 温貴(広)",
    "avg": 0,
    "hr": 0,
    "rbi": 0,
    "sb": 0,
    "obp": 0,
    "slg": 0,
    "ops": 0,
    "risp": 0,
    "era": 2.55,
    "win": 2,
    "lose": 0,
    "k": 23,
    "k9": 8.39,
    "hold": 3,
    "save": 0
  },
  {
    "rank": 27,
    "nameAndTeamName": "コルニエル(広)",
    "avg": 0,
    "hr": 0,
    "rbi": 0,
    "sb": 0,
    "obp": 0,
    "slg": 0,
    "ops": 0,
    "risp": 0,
    "era": 3.49,
    "win": 0,
    "lose": 0,
    "k": 34,
    "k9": 10.8,
    "hold": 3,
    "save": 0
  },
  {
    "rank": 27,
    "nameAndTeamName": "畠 世周(巨)",
    "avg": 0,
    "hr": 0,
    "rbi": 0,
    "sb": 0,
    "obp": 0,
    "slg": 0,
    "ops": 0,
    "risp": 0,
    "era": 3.88,
    "win": 2,
    "lose": 3,
    "k": 49,
    "k9": 9.06,
    "hold": 3,
    "save": 0
  },
  {
    "rank": 27,
    "nameAndTeamName": "平田 真吾(デ)",
    "avg": 0,
    "hr": 0,
    "rbi": 0,
    "sb": 0,
    "obp": 0,
    "slg": 0,
    "ops": 0,
    "risp": 0,
    "era": 5.64,
    "win": 1,
    "lose": 0,
    "k": 21,
    "k9": 8.46,
    "hold": 3,
    "save": 0
  }
]