[
  {
    "rank": 1,
    "name": "森 友哉",
    "team": "西武",
    "avg": 0.337,
    "hr": 21,
    "rbi": 92,
    "sb": 3,
    "obp": 0.423,
    "slg": 0.564,
    "ops": 0.988,
    "risp": 0.395,
    "era": 0,
    "win": 0,
    "lose": 0,
    "k": 0,
    "k9": 0,
    "hold": 0,
    "save": 0
  },
  {
    "rank": 2,
    "name": "吉田 正尚",
    "team": "オリックス",
    "avg": 0.33,
    "hr": 24,
    "rbi": 75,
    "sb": 5,
    "obp": 0.425,
    "slg": 0.55,
    "ops": 0.975,
    "risp": 0.31,
    "era": 0,
    "win": 0,
    "lose": 0,
    "k": 0,
    "k9": 0,
    "hold": 0,
    "save": 0
  },
  {
    "rank": 3,
    "name": "秋山 翔吾",
    "team": "西武",
    "avg": 0.311,
    "hr": 19,
    "rbi": 53,
    "sb": 11,
    "obp": 0.397,
    "slg": 0.481,
    "ops": 0.878,
    "risp": 0.238,
    "era": 0,
    "win": 0,
    "lose": 0,
    "k": 0,
    "k9": 0,
    "hold": 0,
    "save": 0
  },
  {
    "rank": 4,
    "name": "荻野 貴司",
    "team": "ロッテ",
    "avg": 0.3081,
    "hr": 10,
    "rbi": 44,
    "sb": 27,
    "obp": 0.366,
    "slg": 0.474,
    "ops": 0.841,
    "risp": 0.344,
    "era": 0,
    "win": 0,
    "lose": 0,
    "k": 0,
    "k9": 0,
    "hold": 0,
    "save": 0
  },
  {
    "rank": 5,
    "name": "銀次",
    "team": "楽天",
    "avg": 0.3076,
    "hr": 5,
    "rbi": 45,
    "sb": 2,
    "obp": 0.376,
    "slg": 0.391,
    "ops": 0.767,
    "risp": 0.288,
    "era": 0,
    "win": 0,
    "lose": 0,
    "k": 0,
    "k9": 0,
    "hold": 0,
    "save": 0
  },
  {
    "rank": 6,
    "name": "近藤 健介",
    "team": "日本ハム",
    "avg": 0.3,
    "hr": 2,
    "rbi": 55,
    "sb": 1,
    "obp": 0.424,
    "slg": 0.402,
    "ops": 0.826,
    "risp": 0.288,
    "era": 0,
    "win": 0,
    "lose": 0,
    "k": 0,
    "k9": 0,
    "hold": 0,
    "save": 0
  },
  {
    "rank": 7,
    "name": "鈴木 大地",
    "team": "ロッテ",
    "avg": 0.2997,
    "hr": 15,
    "rbi": 63,
    "sb": 3,
    "obp": 0.38,
    "slg": 0.48,
    "ops": 0.86,
    "risp": 0.274,
    "era": 0,
    "win": 0,
    "lose": 0,
    "k": 0,
    "k9": 0,
    "hold": 0,
    "save": 0
  },
  {
    "rank": 8,
    "name": "茂木 栄五郎",
    "team": "楽天",
    "avg": 0.295,
    "hr": 13,
    "rbi": 52,
    "sb": 7,
    "obp": 0.371,
    "slg": 0.449,
    "ops": 0.82,
    "risp": 0.292,
    "era": 0,
    "win": 0,
    "lose": 0,
    "k": 0,
    "k9": 0,
    "hold": 0,
    "save": 0
  },
  {
    "rank": 9,
    "name": "中村 剛也",
    "team": "西武",
    "avg": 0.292,
    "hr": 27,
    "rbi": 111,
    "sb": 2,
    "obp": 0.367,
    "slg": 0.542,
    "ops": 0.908,
    "risp": 0.362,
    "era": 0,
    "win": 0,
    "lose": 0,
    "k": 0,
    "k9": 0,
    "hold": 0,
    "save": 0
  },
  {
    "rank": 10,
    "name": "西川 遥輝",
    "team": "日本ハム",
    "avg": 0.286,
    "hr": 5,
    "rbi": 36,
    "sb": 19,
    "obp": 0.388,
    "slg": 0.384,
    "ops": 0.772,
    "risp": 0.355,
    "era": 0,
    "win": 0,
    "lose": 0,
    "k": 0,
    "k9": 0,
    "hold": 0,
    "save": 0
  }
]