[
  {
    "rank": 1,
    "name": "森 友哉",
    "team": "西武",
    "avg": 0.331,
    "hr": 15,
    "rbi": 68,
    "sb": 3,
    "obp": 0.42,
    "slg": 0.543,
    "ops": 0.963,
    "risp": 0.364,
    "era": 0,
    "win": 0,
    "lose": 0,
    "k": 0,
    "k9": 0,
    "hold": 0,
    "save": 0
  },
  {
    "rank": 2,
    "name": "吉田 正尚",
    "team": "オリックス",
    "avg": 0.311,
    "hr": 20,
    "rbi": 62,
    "sb": 5,
    "obp": 0.413,
    "slg": 0.535,
    "ops": 0.948,
    "risp": 0.286,
    "era": 0,
    "win": 0,
    "lose": 0,
    "k": 0,
    "k9": 0,
    "hold": 0,
    "save": 0
  },
  {
    "rank": 3,
    "name": "ブラッシュ",
    "team": "楽天",
    "avg": 0.259,
    "hr": 22,
    "rbi": 65,
    "sb": 2,
    "obp": 0.389,
    "slg": 0.528,
    "ops": 0.917,
    "risp": 0.3,
    "era": 0,
    "win": 0,
    "lose": 0,
    "k": 0,
    "k9": 0,
    "hold": 0,
    "save": 0
  },
  {
    "rank": 4,
    "name": "山川 穂高",
    "team": "西武",
    "avg": 0.247,
    "hr": 32,
    "rbi": 86,
    "sb": 0,
    "obp": 0.366,
    "slg": 0.534,
    "ops": 0.9,
    "risp": 0.227,
    "era": 0,
    "win": 0,
    "lose": 0,
    "k": 0,
    "k9": 0,
    "hold": 0,
    "save": 0
  },
  {
    "rank": 5,
    "name": "レアード",
    "team": "ロッテ",
    "avg": 0.255,
    "hr": 31,
    "rbi": 75,
    "sb": 0,
    "obp": 0.347,
    "slg": 0.543,
    "ops": 0.89,
    "risp": 0.228,
    "era": 0,
    "win": 0,
    "lose": 0,
    "k": 0,
    "k9": 0,
    "hold": 0,
    "save": 0
  },
  {
    "rank": 6,
    "name": "浅村 栄斗",
    "team": "楽天",
    "avg": 0.276,
    "hr": 25,
    "rbi": 65,
    "sb": 0,
    "obp": 0.375,
    "slg": 0.512,
    "ops": 0.887,
    "risp": 0.252,
    "era": 0,
    "win": 0,
    "lose": 0,
    "k": 0,
    "k9": 0,
    "hold": 0,
    "save": 0
  },
  {
    "rank": 7,
    "name": "鈴木 大地",
    "team": "ロッテ",
    "avg": 0.309,
    "hr": 13,
    "rbi": 52,
    "sb": 3,
    "obp": 0.389,
    "slg": 0.495,
    "ops": 0.8837,
    "risp": 0.274,
    "era": 0,
    "win": 0,
    "lose": 0,
    "k": 0,
    "k9": 0,
    "hold": 0,
    "save": 0
  },
  {
    "rank": 8,
    "name": "秋山 翔吾",
    "team": "西武",
    "avg": 0.304,
    "hr": 15,
    "rbi": 43,
    "sb": 10,
    "obp": 0.403,
    "slg": 0.481,
    "ops": 0.8835,
    "risp": 0.244,
    "era": 0,
    "win": 0,
    "lose": 0,
    "k": 0,
    "k9": 0,
    "hold": 0,
    "save": 0
  },
  {
    "rank": 9,
    "name": "デスパイネ",
    "team": "ソフトバンク",
    "avg": 0.266,
    "hr": 27,
    "rbi": 66,
    "sb": 0,
    "obp": 0.363,
    "slg": 0.514,
    "ops": 0.877,
    "risp": 0.333,
    "era": 0,
    "win": 0,
    "lose": 0,
    "k": 0,
    "k9": 0,
    "hold": 0,
    "save": 0
  },
  {
    "rank": 10,
    "name": "中村 剛也",
    "team": "西武",
    "avg": 0.275,
    "hr": 20,
    "rbi": 78,
    "sb": 0,
    "obp": 0.354,
    "slg": 0.507,
    "ops": 0.861,
    "risp": 0.358,
    "era": 0,
    "win": 0,
    "lose": 0,
    "k": 0,
    "k9": 0,
    "hold": 0,
    "save": 0
  }
]