[
  {
    "rank": 1,
    "name": "金子 侑司",
    "team": "西武",
    "avg": 0.238,
    "hr": 2,
    "rbi": 29,
    "sb": 32,
    "obp": 0.32,
    "slg": 0.284,
    "ops": 0.604,
    "risp": 0.288,
    "era": 0,
    "win": 0,
    "lose": 0,
    "k": 0,
    "k9": 0,
    "hold": 0,
    "save": 0
  },
  {
    "rank": 2,
    "name": "荻野 貴司",
    "team": "ロッテ",
    "avg": 0.309,
    "hr": 7,
    "rbi": 34,
    "sb": 25,
    "obp": 0.365,
    "slg": 0.471,
    "ops": 0.836,
    "risp": 0.324,
    "era": 0,
    "win": 0,
    "lose": 0,
    "k": 0,
    "k9": 0,
    "hold": 0,
    "save": 0
  },
  {
    "rank": 2,
    "name": "福田 周平",
    "team": "オリックス",
    "avg": 0.268,
    "hr": 1,
    "rbi": 24,
    "sb": 25,
    "obp": 0.367,
    "slg": 0.327,
    "ops": 0.694,
    "risp": 0.296,
    "era": 0,
    "win": 0,
    "lose": 0,
    "k": 0,
    "k9": 0,
    "hold": 0,
    "save": 0
  },
  {
    "rank": 4,
    "name": "源田 壮亮",
    "team": "西武",
    "avg": 0.27,
    "hr": 0,
    "rbi": 28,
    "sb": 24,
    "obp": 0.322,
    "slg": 0.339,
    "ops": 0.662,
    "risp": 0.306,
    "era": 0,
    "win": 0,
    "lose": 0,
    "k": 0,
    "k9": 0,
    "hold": 0,
    "save": 0
  },
  {
    "rank": 5,
    "name": "外崎 修汰",
    "team": "西武",
    "avg": 0.259,
    "hr": 16,
    "rbi": 67,
    "sb": 18,
    "obp": 0.33,
    "slg": 0.461,
    "ops": 0.791,
    "risp": 0.274,
    "era": 0,
    "win": 0,
    "lose": 0,
    "k": 0,
    "k9": 0,
    "hold": 0,
    "save": 0
  },
  {
    "rank": 6,
    "name": "西川 遥輝",
    "team": "日本ハム",
    "avg": 0.284,
    "hr": 3,
    "rbi": 31,
    "sb": 17,
    "obp": 0.378,
    "slg": 0.377,
    "ops": 0.754,
    "risp": 0.349,
    "era": 0,
    "win": 0,
    "lose": 0,
    "k": 0,
    "k9": 0,
    "hold": 0,
    "save": 0
  },
  {
    "rank": 6,
    "name": "周東 佑京",
    "team": "ソフトバンク",
    "avg": 0.196,
    "hr": 1,
    "rbi": 4,
    "sb": 17,
    "obp": 0.213,
    "slg": 0.293,
    "ops": 0.506,
    "risp": 0.158,
    "era": 0,
    "win": 0,
    "lose": 0,
    "k": 0,
    "k9": 0,
    "hold": 0,
    "save": 0
  },
  {
    "rank": 8,
    "name": "大城 滉二",
    "team": "オリックス",
    "avg": 0.262,
    "hr": 3,
    "rbi": 28,
    "sb": 11,
    "obp": 0.329,
    "slg": 0.364,
    "ops": 0.694,
    "risp": 0.254,
    "era": 0,
    "win": 0,
    "lose": 0,
    "k": 0,
    "k9": 0,
    "hold": 0,
    "save": 0
  },
  {
    "rank": 8,
    "name": "木村 文紀",
    "team": "西武",
    "avg": 0.225,
    "hr": 6,
    "rbi": 26,
    "sb": 11,
    "obp": 0.266,
    "slg": 0.337,
    "ops": 0.603,
    "risp": 0.18,
    "era": 0,
    "win": 0,
    "lose": 0,
    "k": 0,
    "k9": 0,
    "hold": 0,
    "save": 0
  },
  {
    "rank": 8,
    "name": "中島 卓也",
    "team": "日本ハム",
    "avg": 0.223,
    "hr": 0,
    "rbi": 14,
    "sb": 11,
    "obp": 0.276,
    "slg": 0.253,
    "ops": 0.529,
    "risp": 0.246,
    "era": 0,
    "win": 0,
    "lose": 0,
    "k": 0,
    "k9": 0,
    "hold": 0,
    "save": 0
  }
]